opensyndrome/__init__.py
opensyndrome/cli.py
opensyndrome/converters.py
opensyndrome/filtering.py
opensyndrome/schema.py
opensyndrome/to_be_updated__schema.py
opensyndrome/validators.py
opensyndrome-0.1.0.dist-info/METADATA
opensyndrome-0.1.0.dist-info/WHEEL
opensyndrome-0.1.0.dist-info/entry_points.txt
opensyndrome-0.1.0.dist-info/RECORD
