Metadata-Version: 2.4
Name: opensyndrome
Version: 0.1.0
Author-email: Ana Paula Gomes <apgomes88@gmail.com>
Requires-Python: ~=3.11
Requires-Dist: click<9,>=8.1.8
Requires-Dist: datamodel-code-generator<0.29,>=0.28.1
Requires-Dist: jsonschema<5,>=4.23.0
Requires-Dist: numpy<3,>=2.3.1
Requires-Dist: ollama<0.6,>=0.5.1
Requires-Dist: plotly[express]<7,>=6.1.2
Requires-Dist: pyarrow<21,>=20.0.0
Requires-Dist: pydantic<3,>=2.10.6
Requires-Dist: pygments<3,>=2.19.1
Requires-Dist: python-dotenv<2,>=1.0.1
Requires-Dist: requests>=2.32.5
